chunking_strategy/__init__.py
chunking_strategy/__main__.py
chunking_strategy/benchmarking.py
chunking_strategy/cli.py
chunking_strategy/enhanced_orchestrator.py
chunking_strategy/exceptions.py
chunking_strategy/logging_config.py
chunking_strategy/orchestrator.py
chunking_strategy/core/__init__.py
chunking_strategy/core/adaptive.py
chunking_strategy/core/base.py
chunking_strategy/core/batch.py
chunking_strategy/core/custom_algorithm_loader.py
chunking_strategy/core/custom_config_integration.py
chunking_strategy/core/custom_validation.py
chunking_strategy/core/embeddings.py
chunking_strategy/core/extractors.py
chunking_strategy/core/hardware.py
chunking_strategy/core/metrics.py
chunking_strategy/core/multi_strategy.py
chunking_strategy/core/pipeline.py
chunking_strategy/core/production_benchmark.py
chunking_strategy/core/registry.py
chunking_strategy/core/streaming.py
chunking_strategy/core/tika_integration.py
chunking_strategy/core/universal_auto_registration.py
chunking_strategy/core/universal_framework.py
chunking_strategy/core/universal_implementations.py
chunking_strategy/detectors/__init__.py
chunking_strategy/detectors/content_analyzer.py
chunking_strategy/detectors/encoding_detector.py
chunking_strategy/detectors/file_type_detector.py
chunking_strategy/detectors/language_detector.py
chunking_strategy/strategies/__init__.py
chunking_strategy/strategies/code/__init__.py
chunking_strategy/strategies/code/c_cpp_chunker.py
chunking_strategy/strategies/code/css_chunker.py
chunking_strategy/strategies/code/go_chunker.py
chunking_strategy/strategies/code/java_chunker.py
chunking_strategy/strategies/code/javascript_chunker.py
chunking_strategy/strategies/code/python_chunker.py
chunking_strategy/strategies/code/universal_code_chunker.py
chunking_strategy/strategies/data_formats/__init__.py
chunking_strategy/strategies/data_formats/csv_chunker.py
chunking_strategy/strategies/data_formats/json_chunker.py
chunking_strategy/strategies/document/__init__.py
chunking_strategy-0.4.1.dist-info/licenses/LICENSE
chunking_strategy-0.4.1.dist-info/METADATA
chunking_strategy-0.4.1.dist-info/WHEEL
chunking_strategy-0.4.1.dist-info/entry_points.txt
chunking_strategy-0.4.1.dist-info/top_level.txt
chunking_strategy-0.4.1.dist-info/RECORD
