Metadata-Version: 2.4
Name: chunking-strategy
Version: 0.4.1
Summary: A comprehensive chunking library for text, documents, audio, video, and data streams (Linux and macOS only)
Author-email: Sharan Harsoor <sharanharsoor@gmail.com>
Maintainer-email: Sharan Harsoor <sharanharsoor@gmail.com>
License: MIT
Project-URL: Homepage, https://github.com/sharanharsoor/chunking
Project-URL: Repository, https://github.com/sharanharsoor/chunking
Project-URL: Issues, https://github.com/sharanharsoor/chunking/issues
Project-URL: Changelog, https://github.com/sharanharsoor/chunking/blob/main/CHANGELOG.md
Keywords: chunking,text-processing,document-processing,audio-processing,video-processing,data-streams,content-defined-chunking,semantic-chunking,RAG
Classifier: Development Status :: 3 - Alpha
Classifier: Intended Audience :: Developers
Classifier: License :: OSI Approved :: MIT License
Classifier: Operating System :: POSIX :: Linux
Classifier: Operating System :: MacOS
Classifier: Programming Language :: Python :: 3
Classifier: Programming Language :: Python :: 3.8
Classifier: Programming Language :: Python :: 3.9
Classifier: Programming Language :: Python :: 3.10
Classifier: Programming Language :: Python :: 3.11
Classifier: Programming Language :: Python :: 3.12
Classifier: Topic :: Software Development :: Libraries :: Python Modules
Classifier: Topic :: Text Processing :: General
Classifier: Topic :: Multimedia :: Sound/Audio
Classifier: Topic :: Multimedia :: Video
Requires-Python: >=3.8
License-File: LICENSE
Requires-Dist: pydantic>=2.0.0
Requires-Dist: pyyaml>=6.0
Requires-Dist: click>=8.0.0
Requires-Dist: rich>=13.0.0
Requires-Dist: typing-extensions>=4.0.0
Provides-Extra: dev
Requires-Dist: pytest>=7.0.0; extra == "dev"
Requires-Dist: pytest-cov>=4.0.0; extra == "dev"
Requires-Dist: pytest-asyncio>=0.21.0; extra == "dev"
Requires-Dist: black>=23.0.0; extra == "dev"
Requires-Dist: ruff>=0.1.0; extra == "dev"
Requires-Dist: isort>=5.12.0; extra == "dev"
Requires-Dist: mypy>=1.5.0; extra == "dev"
Requires-Dist: pre-commit>=3.0.0; extra == "dev"
Provides-Extra: text
Requires-Dist: spacy>=3.6.0; extra == "text"
Requires-Dist: nltk>=3.8; extra == "text"
Requires-Dist: sentence-transformers>=5.1.0; extra == "text"
Requires-Dist: huggingface-hub>=0.20.0; extra == "text"
Requires-Dist: tiktoken>=0.5.0; extra == "text"
Provides-Extra: document
Requires-Dist: PyPDF2>=3.0.0; extra == "document"
Requires-Dist: pdfminer.six>=20220524; extra == "document"
Requires-Dist: PyMuPDF>=1.23.0; extra == "document"
Requires-Dist: python-docx>=0.8.11; extra == "document"
Requires-Dist: beautifulsoup4>=4.12.0; extra == "document"
Requires-Dist: lxml>=4.9.0; extra == "document"
Requires-Dist: markdown>=3.5.0; extra == "document"
Provides-Extra: multimedia
Requires-Dist: opencv-python>=4.8.0; extra == "multimedia"
Requires-Dist: Pillow>=10.0.0; extra == "multimedia"
Requires-Dist: librosa>=0.10.0; extra == "multimedia"
Requires-Dist: pydub>=0.25.0; extra == "multimedia"
Requires-Dist: imageio>=2.31.0; extra == "multimedia"
Requires-Dist: moviepy>=1.0.3; extra == "multimedia"
Provides-Extra: ml
Requires-Dist: scikit-learn>=1.3.0; extra == "ml"
Requires-Dist: numpy>=1.24.0; extra == "ml"
Requires-Dist: torch>=2.0.0; extra == "ml"
Requires-Dist: transformers>=4.30.0; extra == "ml"
Requires-Dist: bitsandbytes>=0.47.0; extra == "ml"
Requires-Dist: fsspec<2025.0.0,>=2023.1.0; extra == "ml"
Provides-Extra: detection
Requires-Dist: python-magic>=0.4.27; extra == "detection"
Requires-Dist: chardet>=5.2.0; extra == "detection"
Requires-Dist: langdetect>=1.0.9; extra == "detection"
Provides-Extra: hardware
Requires-Dist: psutil>=5.9.0; extra == "hardware"
Requires-Dist: GPUtil>=1.4.0; extra == "hardware"
Requires-Dist: nvidia-ml-py3>=7.352.0; extra == "hardware"
Provides-Extra: tika
Requires-Dist: tika>=2.6.0; extra == "tika"
Requires-Dist: python-magic>=0.4.27; extra == "tika"
Provides-Extra: vectordb
Requires-Dist: qdrant-client>=1.6.0; extra == "vectordb"
Requires-Dist: weaviate-client>=3.24.0; extra == "vectordb"
Requires-Dist: pinecone-client>=2.2.0; extra == "vectordb"
Provides-Extra: streamlit
Requires-Dist: streamlit>=1.28.0; extra == "streamlit"
Requires-Dist: plotly>=5.17.0; extra == "streamlit"
Provides-Extra: langchain
Requires-Dist: langchain>=0.0.300; extra == "langchain"
Requires-Dist: langchain-community>=0.0.25; extra == "langchain"
Requires-Dist: chromadb>=0.4.15; extra == "langchain"
Provides-Extra: all
Requires-Dist: chunking-strategy[detection,dev,document,hardware,langchain,ml,multimedia,streamlit,text,tika,vectordb]; extra == "all"
Dynamic: license-file
